kanban_python/__init__.py
kanban_python/app.py
kanban_python/cli_parser.py
kanban_python/config.py
kanban_python/constants.py
kanban_python/controls.py
kanban_python/interface.py
kanban_python/utils.py
kanban_python-0.6.0.dist-info/METADATA
kanban_python-0.6.0.dist-info/WHEEL
kanban_python-0.6.0.dist-info/entry_points.txt
kanban_python-0.6.0.dist-info/licenses/AUTHORS.md
kanban_python-0.6.0.dist-info/licenses/LICENSE.txt
kanban_python-0.6.0.dist-info/RECORD
