Metadata-Version: 2.4
Name: kanban-python
Version: 0.6.0
Summary: Terminal Kanban App written in Python
Project-URL: Repository, https://github.com/Zaloog/kanban-python
Project-URL: Changelog, https://github.com/Zaloog/kanban-python/blob/main/CHANGELOG.md
Author-email: Zaloog <gramslars@gmail.com>
License: The MIT License (MIT)
License-File: AUTHORS.md
License-File: LICENSE.txt
Classifier: Development Status :: 3 - Alpha
Classifier: License :: OSI Approved :: MIT License
Classifier: Operating System :: OS Independent
Classifier: Programming Language :: Python
Classifier: Programming Language :: Python :: 3 :: Only
Classifier: Programming Language :: Python :: 3.9
Classifier: Programming Language :: Python :: 3.10
Classifier: Programming Language :: Python :: 3.11
Classifier: Programming Language :: Python :: 3.12
Classifier: Programming Language :: Python :: 3.13
Requires-Python: >=3.9
Requires-Dist: platformdirs>=4.3.6
Requires-Dist: rich>=13.9.4
